brainspy/__init__.py
brainspy/__main__.py
brainspy-1.0.0.dist-info/METADATA
brainspy-1.0.0.dist-info/WHEEL
brainspy-1.0.0.dist-info/top_level.txt
brainspy-1.0.0.dist-info/RECORD
