Metadata-Version: 2.1
Name: brainspy
Version: 1.0.0
Summary: A python package to support research on different nano-scale materials for creating hardware accelerators in the context of deep neural networks.
Author: Unai Alegre-Ibarra et al.
Author-email: u.alegre@utwente.nl
License: GPL-3.0
Keywords: pytorch,nano,material,hardware acceleration,deep neural networks
Classifier: Development Status :: 5 - Production/Stable
Classifier: Topic :: Scientific/Engineering :: Artificial Intelligence
Classifier: Intended Audience :: Science/Research
Classifier: Programming Language :: Python :: 3.9
Classifier: License :: OSI Approved :: GNU General Public License v3 (GPLv3)
Requires-Python: ==3.9.1
Requires-Dist: torch (~=1.11)
Requires-Dist: torchvision (~=0.12)
Requires-Dist: matplotlib (~=3.4)
Requires-Dist: nidaqmx (~=0.6)
Requires-Dist: tqdm (~=4.63)
Requires-Dist: PyYAML (==6.0)
Requires-Dist: unittest2 (==1.1.0)
Requires-Dist: pytest (==7.1.2)
Requires-Dist: pytest-cov (==3.0.0)
Requires-Dist: coverage (==6.4)
